{"stat.useItem.139":11,"stat.useItem.381":1,"stat.useItem.3":235,"stat.useItem.65":16,"stat.useItem.351":95,"achievement.exploreAllBiomes":{"value":0,"progress":["Forest","Desert","Jungle"]},"stat.useItem.324":1,"stat.useItem.24":14,"stat.useItem.126":76,"stat.useItem.53":47,"stat.useItem.48":2,"stat.useItem.89":10,"achievement.openInventory":121,"stat.useItem.96":132,"stat.useItem.50":1,"stat.useItem.323":92,"stat.useItem.5":257,"stat.useItem.31":2,"stat.flyOneCm":852766,"stat.useItem.33":9,"stat.useItem.160":22,"stat.useItem.38":3,"stat.damageTaken":-2,"stat.useItem.121":34,"stat.useItem.4":2,"stat.useItem.152":2,"stat.useItem.69":5,"stat.useItem.45":38,"stat.useItem.136":227,"stat.drop":5,"stat.useItem.18":137,"stat.useItem.120":1,"stat.useItem.80":1,"stat.useItem.154":1,"stat.useItem.54":3,"stat.playOneMinute":124325,"stat.useItem.109":44,"stat.useItem.17":232,"stat.useItem.123":2,"stat.useItem.107":4,"stat.useItem.37":1,"stat.useItem.108":191,"stat.useItem.85":52,"stat.deaths":2,"stat.jump":371,"stat.useItem.390":9,"stat.useItem.98":74,"stat.useItem.102":80,"stat.walkOneCm":149789,"stat.useItem.145":3,"stat.useItem.44":158,"stat.useItem.128":38,"stat.useItem.67":8}